{
  "name": "Bangs",
  "type_name": "hair",
  "layer_1": {
    "zPos": 120,
    "male": "hair/bangs/male/",
    "muscular": "hair/bangs/male/",
    "female": "hair/bangs/female/",
    "pregnant": "hair/bangs/female/",
    "teen": "hair/bangs/male/"
  },
  "variants": [
    "blonde",
    "ash",
    "sandy",
    "platinum",
    "strawberry",
    "redhead",
    "ginger",
    "carrot",
    "chestnut",
    "light brown",
    "dark brown",
    "black",
    "raven",
    "dark gray",
    "gray",
    "white",
    "red",
    "orange",
    "gold",
    "green",
    "blue",
    "navy",
    "violet",
    "purple",
    "pink",
    "rose"
  ],
  "credits": [
    {
      "file": "hair/bangs/male/blonde.png",
      "notes": "",
      "authors": [
        "Manuel Riecke (MrBeast)"
      ],
      "licenses": [
        "CC-BY-SA 3.0",
        "GPL 3.0"
      ],
      "urls": [
        "https://opengameart.org/content/liberated-pixel-cup-lpc-base-assets-sprites-map-tiles"
      ]
    },
    {
      "file": "hair/bangs/female/blonde.png",
      "notes": "",
      "authors": [
        "Manuel Riecke (MrBeast)"
      ],
      "licenses": [
        "CC-BY-SA 3.0",
        "GPL 3.0"
      ],
      "urls": [
        "https://opengameart.org/content/liberated-pixel-cup-lpc-base-assets-sprites-map-tiles"
      ]
    },
    {
      "file": "hair/bangs/male/ash.png",
      "notes": "",
      "authors": [
        "Manuel Riecke (MrBeast)"
      ],
      "licenses": [
        "CC-BY-SA 3.0",
        "GPL 3.0"
      ],
      "urls": [
        "https://opengameart.org/content/liberated-pixel-cup-lpc-base-assets-sprites-map-tiles"
      ]
    },
    {
      "file": "hair/bangs/female/ash.png",
      "notes": "",
      "authors": [
        "Manuel Riecke (MrBeast)"
      ],
      "licenses": [
        "CC-BY-SA 3.0",
        "GPL 3.0"
      ],
      "urls": [
        "https://opengameart.org/content/liberated-pixel-cup-lpc-base-assets-sprites-map-tiles"
      ]
    },
    {
      "file": "hair/bangs/male/sandy.png",
      "notes": "",
      "authors": [
        "Manuel Riecke (MrBeast)"
      ],
      "licenses": [
        "CC-BY-SA 3.0",
        "GPL 3.0"
      ],
      "urls": [
        "https://opengameart.org/content/liberated-pixel-cup-lpc-base-assets-sprites-map-tiles"
      ]
    },
    {
      "file": "hair/bangs/female/sandy.png",
      "notes": "",
      "authors": [
        "Manuel Riecke (MrBeast)"
      ],
      "licenses": [
        "CC-BY-SA 3.0",
        "GPL 3.0"
      ],
      "urls": [
        "https://opengameart.org/content/liberated-pixel-cup-lpc-base-assets-sprites-map-tiles"
      ]
    },
    {
      "file": "hair/bangs/male/platinum.png",
      "notes": "",
      "authors": [
        "Manuel Riecke (MrBeast)"
      ],
      "licenses": [
        "CC-BY-SA 3.0",
        "GPL 3.0"
      ],
      "urls": [
        "https://opengameart.org/content/liberated-pixel-cup-lpc-base-assets-sprites-map-tiles"
      ]
    },
    {
      "file": "hair/bangs/female/platinum.png",
      "notes": "",
      "authors": [
        "Manuel Riecke (MrBeast)"
      ],
      "licenses": [
        "CC-BY-SA 3.0",
        "GPL 3.0"
      ],
      "urls": [
        "https://opengameart.org/content/liberated-pixel-cup-lpc-base-assets-sprites-map-tiles"
      ]
    },
    {
      "file": "hair/bangs/male/strawberry.png",
      "notes": "",
      "authors": [
        "Manuel Riecke (MrBeast)"
      ],
      "licenses": [
        "CC-BY-SA 3.0",
        "GPL 3.0"
      ],
      "urls": [
        "https://opengameart.org/content/liberated-pixel-cup-lpc-base-assets-sprites-map-tiles"
      ]
    },
    {
      "file": "hair/bangs/female/strawberry.png",
      "notes": "",
      "authors": [
        "Manuel Riecke (MrBeast)"
      ],
      "licenses": [
        "CC-BY-SA 3.0",
        "GPL 3.0"
      ],
      "urls": [
        "https://opengameart.org/content/liberated-pixel-cup-lpc-base-assets-sprites-map-tiles"
      ]
    },
    {
      "file": "hair/bangs/male/redhead.png",
      "notes": "",
      "authors": [
        "Manuel Riecke (MrBeast)"
      ],
      "licenses": [
        "CC-BY-SA 3.0",
        "GPL 3.0"
      ],
      "urls": [
        "https://opengameart.org/content/liberated-pixel-cup-lpc-base-assets-sprites-map-tiles"
      ]
    },
    {
      "file": "hair/bangs/female/redhead.png",
      "notes": "",
      "authors": [
        "Manuel Riecke (MrBeast)"
      ],
      "licenses": [
        "CC-BY-SA 3.0",
        "GPL 3.0"
      ],
      "urls": [
        "https://opengameart.org/content/liberated-pixel-cup-lpc-base-assets-sprites-map-tiles"
      ]
    },
    {
      "file": "hair/bangs/male/ginger.png",
      "notes": "",
      "authors": [
        "Manuel Riecke (MrBeast)"
      ],
      "licenses": [
        "CC-BY-SA 3.0",
        "GPL 3.0"
      ],
      "urls": [
        "https://opengameart.org/content/liberated-pixel-cup-lpc-base-assets-sprites-map-tiles"
      ]
    },
    {
      "file": "hair/bangs/female/ginger.png",
      "notes": "",
      "authors": [
        "Manuel Riecke (MrBeast)"
      ],
      "licenses": [
        "CC-BY-SA 3.0",
        "GPL 3.0"
      ],
      "urls": [
        "https://opengameart.org/content/liberated-pixel-cup-lpc-base-assets-sprites-map-tiles"
      ]
    },
    {
      "file": "hair/bangs/male/carrot.png",
      "notes": "",
      "authors": [
        "Manuel Riecke (MrBeast)"
      ],
      "licenses": [
        "CC-BY-SA 3.0",
        "GPL 3.0"
      ],
      "urls": [
        "https://opengameart.org/content/liberated-pixel-cup-lpc-base-assets-sprites-map-tiles"
      ]
    },
    {
      "file": "hair/bangs/female/carrot.png",
      "notes": "",
      "authors": [
        "Manuel Riecke (MrBeast)"
      ],
      "licenses": [
        "CC-BY-SA 3.0",
        "GPL 3.0"
      ],
      "urls": [
        "https://opengameart.org/content/liberated-pixel-cup-lpc-base-assets-sprites-map-tiles"
      ]
    },
    {
      "file": "hair/bangs/male/chestnut.png",
      "notes": "",
      "authors": [
        "Manuel Riecke (MrBeast)"
      ],
      "licenses": [
        "CC-BY-SA 3.0",
        "GPL 3.0"
      ],
      "urls": [
        "https://opengameart.org/content/liberated-pixel-cup-lpc-base-assets-sprites-map-tiles"
      ]
    },
    {
      "file": "hair/bangs/female/chestnut.png",
      "notes": "",
      "authors": [
        "Manuel Riecke (MrBeast)"
      ],
      "licenses": [
        "CC-BY-SA 3.0",
        "GPL 3.0"
      ],
      "urls": [
        "https://opengameart.org/content/liberated-pixel-cup-lpc-base-assets-sprites-map-tiles"
      ]
    },
    {
      "file": "hair/bangs/male/black.png",
      "notes": "",
      "authors": [
        "Manuel Riecke (MrBeast)"
      ],
      "licenses": [
        "CC-BY-SA 3.0",
        "GPL 3.0"
      ],
      "urls": [
        "https://opengameart.org/content/liberated-pixel-cup-lpc-base-assets-sprites-map-tiles"
      ]
    },
    {
      "file": "hair/bangs/female/black.png",
      "notes": "",
      "authors": [
        "Manuel Riecke (MrBeast)"
      ],
      "licenses": [
        "CC-BY-SA 3.0",
        "GPL 3.0"
      ],
      "urls": [
        "https://opengameart.org/content/liberated-pixel-cup-lpc-base-assets-sprites-map-tiles"
      ]
    },
    {
      "file": "hair/bangs/male/raven.png",
      "notes": "",
      "authors": [
        "Manuel Riecke (MrBeast)"
      ],
      "licenses": [
        "CC-BY-SA 3.0",
        "GPL 3.0"
      ],
      "urls": [
        "https://opengameart.org/content/liberated-pixel-cup-lpc-base-assets-sprites-map-tiles"
      ]
    },
    {
      "file": "hair/bangs/female/raven.png",
      "notes": "",
      "authors": [
        "Manuel Riecke (MrBeast)"
      ],
      "licenses": [
        "CC-BY-SA 3.0",
        "GPL 3.0"
      ],
      "urls": [
        "https://opengameart.org/content/liberated-pixel-cup-lpc-base-assets-sprites-map-tiles"
      ]
    },
    {
      "file": "hair/bangs/male/gray.png",
      "notes": "",
      "authors": [
        "Manuel Riecke (MrBeast)"
      ],
      "licenses": [
        "CC-BY-SA 3.0",
        "GPL 3.0"
      ],
      "urls": [
        "https://opengameart.org/content/liberated-pixel-cup-lpc-base-assets-sprites-map-tiles"
      ]
    },
    {
      "file": "hair/bangs/female/gray.png",
      "notes": "",
      "authors": [
        "Manuel Riecke (MrBeast)"
      ],
      "licenses": [
        "CC-BY-SA 3.0",
        "GPL 3.0"
      ],
      "urls": [
        "https://opengameart.org/content/liberated-pixel-cup-lpc-base-assets-sprites-map-tiles"
      ]
    },
    {
      "file": "hair/bangs/male/white.png",
      "notes": "",
      "authors": [
        "Manuel Riecke (MrBeast)"
      ],
      "licenses": [
        "CC-BY-SA 3.0",
        "GPL 3.0"
      ],
      "urls": [
        "https://opengameart.org/content/liberated-pixel-cup-lpc-base-assets-sprites-map-tiles"
      ]
    },
    {
      "file": "hair/bangs/female/white.png",
      "notes": "",
      "authors": [
        "Manuel Riecke (MrBeast)"
      ],
      "licenses": [
        "CC-BY-SA 3.0",
        "GPL 3.0"
      ],
      "urls": [
        "https://opengameart.org/content/liberated-pixel-cup-lpc-base-assets-sprites-map-tiles"
      ]
    },
    {
      "file": "hair/bangs/male/red.png",
      "notes": "",
      "authors": [
        "Manuel Riecke (MrBeast)"
      ],
      "licenses": [
        "CC-BY-SA 3.0",
        "GPL 3.0"
      ],
      "urls": [
        "https://opengameart.org/content/liberated-pixel-cup-lpc-base-assets-sprites-map-tiles"
      ]
    },
    {
      "file": "hair/bangs/female/red.png",
      "notes": "",
      "authors": [
        "Manuel Riecke (MrBeast)"
      ],
      "licenses": [
        "CC-BY-SA 3.0",
        "GPL 3.0"
      ],
      "urls": [
        "https://opengameart.org/content/liberated-pixel-cup-lpc-base-assets-sprites-map-tiles"
      ]
    },
    {
      "file": "hair/bangs/male/orange.png",
      "notes": "",
      "authors": [
        "Manuel Riecke (MrBeast)"
      ],
      "licenses": [
        "CC-BY-SA 3.0",
        "GPL 3.0"
      ],
      "urls": [
        "https://opengameart.org/content/liberated-pixel-cup-lpc-base-assets-sprites-map-tiles"
      ]
    },
    {
      "file": "hair/bangs/female/orange.png",
      "notes": "",
      "authors": [
        "Manuel Riecke (MrBeast)"
      ],
      "licenses": [
        "CC-BY-SA 3.0",
        "GPL 3.0"
      ],
      "urls": [
        "https://opengameart.org/content/liberated-pixel-cup-lpc-base-assets-sprites-map-tiles"
      ]
    },
    {
      "file": "hair/bangs/male/gold.png",
      "notes": "",
      "authors": [
        "Manuel Riecke (MrBeast)"
      ],
      "licenses": [
        "CC-BY-SA 3.0",
        "GPL 3.0"
      ],
      "urls": [
        "https://opengameart.org/content/liberated-pixel-cup-lpc-base-assets-sprites-map-tiles"
      ]
    },
    {
      "file": "hair/bangs/female/gold.png",
      "notes": "",
      "authors": [
        "Manuel Riecke (MrBeast)"
      ],
      "licenses": [
        "CC-BY-SA 3.0",
        "GPL 3.0"
      ],
      "urls": [
        "https://opengameart.org/content/liberated-pixel-cup-lpc-base-assets-sprites-map-tiles"
      ]
    },
    {
      "file": "hair/bangs/male/green.png",
      "notes": "",
      "authors": [
        "Manuel Riecke (MrBeast)"
      ],
      "licenses": [
        "CC-BY-SA 3.0",
        "GPL 3.0"
      ],
      "urls": [
        "https://opengameart.org/content/liberated-pixel-cup-lpc-base-assets-sprites-map-tiles"
      ]
    },
    {
      "file": "hair/bangs/female/green.png",
      "notes": "",
      "authors": [
        "Manuel Riecke (MrBeast)"
      ],
      "licenses": [
        "CC-BY-SA 3.0",
        "GPL 3.0"
      ],
      "urls": [
        "https://opengameart.org/content/liberated-pixel-cup-lpc-base-assets-sprites-map-tiles"
      ]
    },
    {
      "file": "hair/bangs/male/blue.png",
      "notes": "",
      "authors": [
        "Manuel Riecke (MrBeast)"
      ],
      "licenses": [
        "CC-BY-SA 3.0",
        "GPL 3.0"
      ],
      "urls": [
        "https://opengameart.org/content/liberated-pixel-cup-lpc-base-assets-sprites-map-tiles"
      ]
    },
    {
      "file": "hair/bangs/female/blue.png",
      "notes": "",
      "authors": [
        "Manuel Riecke (MrBeast)"
      ],
      "licenses": [
        "CC-BY-SA 3.0",
        "GPL 3.0"
      ],
      "urls": [
        "https://opengameart.org/content/liberated-pixel-cup-lpc-base-assets-sprites-map-tiles"
      ]
    },
    {
      "file": "hair/bangs/male/navy.png",
      "notes": "",
      "authors": [
        "Manuel Riecke (MrBeast)"
      ],
      "licenses": [
        "CC-BY-SA 3.0",
        "GPL 3.0"
      ],
      "urls": [
        "https://opengameart.org/content/liberated-pixel-cup-lpc-base-assets-sprites-map-tiles"
      ]
    },
    {
      "file": "hair/bangs/female/navy.png",
      "notes": "",
      "authors": [
        "Manuel Riecke (MrBeast)"
      ],
      "licenses": [
        "CC-BY-SA 3.0",
        "GPL 3.0"
      ],
      "urls": [
        "https://opengameart.org/content/liberated-pixel-cup-lpc-base-assets-sprites-map-tiles"
      ]
    },
    {
      "file": "hair/bangs/male/violet.png",
      "notes": "",
      "authors": [
        "Manuel Riecke (MrBeast)"
      ],
      "licenses": [
        "CC-BY-SA 3.0",
        "GPL 3.0"
      ],
      "urls": [
        "https://opengameart.org/content/liberated-pixel-cup-lpc-base-assets-sprites-map-tiles"
      ]
    },
    {
      "file": "hair/bangs/female/violet.png",
      "notes": "",
      "authors": [
        "Manuel Riecke (MrBeast)"
      ],
      "licenses": [
        "CC-BY-SA 3.0",
        "GPL 3.0"
      ],
      "urls": [
        "https://opengameart.org/content/liberated-pixel-cup-lpc-base-assets-sprites-map-tiles"
      ]
    },
    {
      "file": "hair/bangs/male/purple.png",
      "notes": "",
      "authors": [
        "Manuel Riecke (MrBeast)"
      ],
      "licenses": [
        "CC-BY-SA 3.0",
        "GPL 3.0"
      ],
      "urls": [
        "https://opengameart.org/content/liberated-pixel-cup-lpc-base-assets-sprites-map-tiles"
      ]
    },
    {
      "file": "hair/bangs/female/purple.png",
      "notes": "",
      "authors": [
        "Manuel Riecke (MrBeast)"
      ],
      "licenses": [
        "CC-BY-SA 3.0",
        "GPL 3.0"
      ],
      "urls": [
        "https://opengameart.org/content/liberated-pixel-cup-lpc-base-assets-sprites-map-tiles"
      ]
    },
    {
      "file": "hair/bangs/male/pink.png",
      "notes": "",
      "authors": [
        "Manuel Riecke (MrBeast)"
      ],
      "licenses": [
        "CC-BY-SA 3.0",
        "GPL 3.0"
      ],
      "urls": [
        "https://opengameart.org/content/liberated-pixel-cup-lpc-base-assets-sprites-map-tiles"
      ]
    },
    {
      "file": "hair/bangs/female/pink.png",
      "notes": "",
      "authors": [
        "Manuel Riecke (MrBeast)"
      ],
      "licenses": [
        "CC-BY-SA 3.0",
        "GPL 3.0"
      ],
      "urls": [
        "https://opengameart.org/content/liberated-pixel-cup-lpc-base-assets-sprites-map-tiles"
      ]
    },
    {
      "file": "hair/bangs/male/rose.png",
      "notes": "",
      "authors": [
        "Manuel Riecke (MrBeast)"
      ],
      "licenses": [
        "CC-BY-SA 3.0",
        "GPL 3.0"
      ],
      "urls": [
        "https://opengameart.org/content/liberated-pixel-cup-lpc-base-assets-sprites-map-tiles"
      ]
    },
    {
      "file": "hair/bangs/female/rose.png",
      "notes": "",
      "authors": [
        "Manuel Riecke (MrBeast)"
      ],
      "licenses": [
        "CC-BY-SA 3.0",
        "GPL 3.0"
      ],
      "urls": [
        "https://opengameart.org/content/liberated-pixel-cup-lpc-base-assets-sprites-map-tiles"
      ]
    }
  ]
}