{
  "name": "Curtains",
  "type_name": "hair",
  "layer_1": {
    "zPos": 120,
    "male": "hair/curtains/male/",
    "muscular": "hair/curtains/male/",
    "female": "hair/curtains/female/",
    "pregnant": "hair/curtains/female/",
    "teen": "hair/curtains/male/"
  },
  "variants": [
    "blonde",
    "ash",
    "sandy",
    "platinum",
    "strawberry",
    "redhead",
    "ginger",
    "carrot",
    "chestnut",
    "light brown",
    "dark brown",
    "black",
    "raven",
    "dark gray",
    "gray",
    "white",
    "red",
    "orange",
    "gold",
    "green",
    "blue",
    "navy",
    "violet",
    "purple",
    "pink",
    "rose"
  ],
  "credits": [
    {
      "file": "hair/curtains/male/blonde.png",
      "notes": "",
      "authors": [
        "Mandi Paugh",
        "bluecarrot16"
      ],
      "licenses": [
        "GPL 2.0",
        "GPL 3.0",
        "CC-BY 3.0"
      ],
      "urls": [
        "https://opengameart.org/content/star-overland",
        "https://opengameart.org/content/lpc-hair"
      ]
    },
    {
      "file": "hair/curtains/female/blonde.png",
      "notes": "",
      "authors": [
        "Mandi Paugh",
        "bluecarrot16"
      ],
      "licenses": [
        "GPL 2.0",
        "GPL 3.0",
        "CC-BY 3.0"
      ],
      "urls": [
        "https://opengameart.org/content/star-overland",
        "https://opengameart.org/content/lpc-hair"
      ]
    },
    {
      "file": "hair/curtains/male/ash.png",
      "notes": "",
      "authors": [
        "Mandi Paugh",
        "bluecarrot16"
      ],
      "licenses": [
        "GPL 2.0",
        "GPL 3.0",
        "CC-BY 3.0"
      ],
      "urls": [
        "https://opengameart.org/content/star-overland",
        "https://opengameart.org/content/lpc-hair"
      ]
    },
    {
      "file": "hair/curtains/female/ash.png",
      "notes": "",
      "authors": [
        "Mandi Paugh",
        "bluecarrot16"
      ],
      "licenses": [
        "GPL 2.0",
        "GPL 3.0",
        "CC-BY 3.0"
      ],
      "urls": [
        "https://opengameart.org/content/star-overland",
        "https://opengameart.org/content/lpc-hair"
      ]
    },
    {
      "file": "hair/curtains/male/sandy.png",
      "notes": "",
      "authors": [
        "Mandi Paugh",
        "bluecarrot16"
      ],
      "licenses": [
        "GPL 2.0",
        "GPL 3.0",
        "CC-BY 3.0"
      ],
      "urls": [
        "https://opengameart.org/content/star-overland",
        "https://opengameart.org/content/lpc-hair"
      ]
    },
    {
      "file": "hair/curtains/female/sandy.png",
      "notes": "",
      "authors": [
        "Mandi Paugh",
        "bluecarrot16"
      ],
      "licenses": [
        "GPL 2.0",
        "GPL 3.0",
        "CC-BY 3.0"
      ],
      "urls": [
        "https://opengameart.org/content/star-overland",
        "https://opengameart.org/content/lpc-hair"
      ]
    },
    {
      "file": "hair/curtains/male/platinum.png",
      "notes": "",
      "authors": [
        "Mandi Paugh",
        "bluecarrot16"
      ],
      "licenses": [
        "GPL 2.0",
        "GPL 3.0",
        "CC-BY 3.0"
      ],
      "urls": [
        "https://opengameart.org/content/star-overland",
        "https://opengameart.org/content/lpc-hair"
      ]
    },
    {
      "file": "hair/curtains/female/platinum.png",
      "notes": "",
      "authors": [
        "Mandi Paugh",
        "bluecarrot16"
      ],
      "licenses": [
        "GPL 2.0",
        "GPL 3.0",
        "CC-BY 3.0"
      ],
      "urls": [
        "https://opengameart.org/content/star-overland",
        "https://opengameart.org/content/lpc-hair"
      ]
    },
    {
      "file": "hair/curtains/male/strawberry.png",
      "notes": "",
      "authors": [
        "Mandi Paugh",
        "bluecarrot16"
      ],
      "licenses": [
        "GPL 2.0",
        "GPL 3.0",
        "CC-BY 3.0"
      ],
      "urls": [
        "https://opengameart.org/content/star-overland",
        "https://opengameart.org/content/lpc-hair"
      ]
    },
    {
      "file": "hair/curtains/female/strawberry.png",
      "notes": "",
      "authors": [
        "Mandi Paugh",
        "bluecarrot16"
      ],
      "licenses": [
        "GPL 2.0",
        "GPL 3.0",
        "CC-BY 3.0"
      ],
      "urls": [
        "https://opengameart.org/content/star-overland",
        "https://opengameart.org/content/lpc-hair"
      ]
    },
    {
      "file": "hair/curtains/male/redhead.png",
      "notes": "",
      "authors": [
        "Mandi Paugh",
        "bluecarrot16"
      ],
      "licenses": [
        "GPL 2.0",
        "GPL 3.0",
        "CC-BY 3.0"
      ],
      "urls": [
        "https://opengameart.org/content/star-overland",
        "https://opengameart.org/content/lpc-hair"
      ]
    },
    {
      "file": "hair/curtains/female/redhead.png",
      "notes": "",
      "authors": [
        "Mandi Paugh",
        "bluecarrot16"
      ],
      "licenses": [
        "GPL 2.0",
        "GPL 3.0",
        "CC-BY 3.0"
      ],
      "urls": [
        "https://opengameart.org/content/star-overland",
        "https://opengameart.org/content/lpc-hair"
      ]
    },
    {
      "file": "hair/curtains/male/ginger.png",
      "notes": "",
      "authors": [
        "Mandi Paugh",
        "bluecarrot16"
      ],
      "licenses": [
        "GPL 2.0",
        "GPL 3.0",
        "CC-BY 3.0"
      ],
      "urls": [
        "https://opengameart.org/content/star-overland",
        "https://opengameart.org/content/lpc-hair"
      ]
    },
    {
      "file": "hair/curtains/female/ginger.png",
      "notes": "",
      "authors": [
        "Mandi Paugh",
        "bluecarrot16"
      ],
      "licenses": [
        "GPL 2.0",
        "GPL 3.0",
        "CC-BY 3.0"
      ],
      "urls": [
        "https://opengameart.org/content/star-overland",
        "https://opengameart.org/content/lpc-hair"
      ]
    },
    {
      "file": "hair/curtains/male/carrot.png",
      "notes": "",
      "authors": [
        "Mandi Paugh",
        "bluecarrot16"
      ],
      "licenses": [
        "GPL 2.0",
        "GPL 3.0",
        "CC-BY 3.0"
      ],
      "urls": [
        "https://opengameart.org/content/star-overland",
        "https://opengameart.org/content/lpc-hair"
      ]
    },
    {
      "file": "hair/curtains/female/carrot.png",
      "notes": "",
      "authors": [
        "Mandi Paugh",
        "bluecarrot16"
      ],
      "licenses": [
        "GPL 2.0",
        "GPL 3.0",
        "CC-BY 3.0"
      ],
      "urls": [
        "https://opengameart.org/content/star-overland",
        "https://opengameart.org/content/lpc-hair"
      ]
    },
    {
      "file": "hair/curtains/male/chestnut.png",
      "notes": "",
      "authors": [
        "Mandi Paugh",
        "bluecarrot16"
      ],
      "licenses": [
        "GPL 2.0",
        "GPL 3.0",
        "CC-BY 3.0"
      ],
      "urls": [
        "https://opengameart.org/content/star-overland",
        "https://opengameart.org/content/lpc-hair"
      ]
    },
    {
      "file": "hair/curtains/female/chestnut.png",
      "notes": "",
      "authors": [
        "Mandi Paugh",
        "bluecarrot16"
      ],
      "licenses": [
        "GPL 2.0",
        "GPL 3.0",
        "CC-BY 3.0"
      ],
      "urls": [
        "https://opengameart.org/content/star-overland",
        "https://opengameart.org/content/lpc-hair"
      ]
    },
    {
      "file": "hair/curtains/male/black.png",
      "notes": "",
      "authors": [
        "Mandi Paugh",
        "bluecarrot16"
      ],
      "licenses": [
        "GPL 2.0",
        "GPL 3.0",
        "CC-BY 3.0"
      ],
      "urls": [
        "https://opengameart.org/content/star-overland",
        "https://opengameart.org/content/lpc-hair"
      ]
    },
    {
      "file": "hair/curtains/female/black.png",
      "notes": "",
      "authors": [
        "Mandi Paugh",
        "bluecarrot16"
      ],
      "licenses": [
        "GPL 2.0",
        "GPL 3.0",
        "CC-BY 3.0"
      ],
      "urls": [
        "https://opengameart.org/content/star-overland",
        "https://opengameart.org/content/lpc-hair"
      ]
    },
    {
      "file": "hair/curtains/male/raven.png",
      "notes": "",
      "authors": [
        "Mandi Paugh",
        "bluecarrot16"
      ],
      "licenses": [
        "GPL 2.0",
        "GPL 3.0",
        "CC-BY 3.0"
      ],
      "urls": [
        "https://opengameart.org/content/star-overland",
        "https://opengameart.org/content/lpc-hair"
      ]
    },
    {
      "file": "hair/curtains/female/raven.png",
      "notes": "",
      "authors": [
        "Mandi Paugh",
        "bluecarrot16"
      ],
      "licenses": [
        "GPL 2.0",
        "GPL 3.0",
        "CC-BY 3.0"
      ],
      "urls": [
        "https://opengameart.org/content/star-overland",
        "https://opengameart.org/content/lpc-hair"
      ]
    },
    {
      "file": "hair/curtains/male/gray.png",
      "notes": "",
      "authors": [
        "Mandi Paugh",
        "bluecarrot16"
      ],
      "licenses": [
        "GPL 2.0",
        "GPL 3.0",
        "CC-BY 3.0"
      ],
      "urls": [
        "https://opengameart.org/content/star-overland",
        "https://opengameart.org/content/lpc-hair"
      ]
    },
    {
      "file": "hair/curtains/female/gray.png",
      "notes": "",
      "authors": [
        "Mandi Paugh",
        "bluecarrot16"
      ],
      "licenses": [
        "GPL 2.0",
        "GPL 3.0",
        "CC-BY 3.0"
      ],
      "urls": [
        "https://opengameart.org/content/star-overland",
        "https://opengameart.org/content/lpc-hair"
      ]
    },
    {
      "file": "hair/curtains/male/white.png",
      "notes": "",
      "authors": [
        "Mandi Paugh",
        "bluecarrot16"
      ],
      "licenses": [
        "GPL 2.0",
        "GPL 3.0",
        "CC-BY 3.0"
      ],
      "urls": [
        "https://opengameart.org/content/star-overland",
        "https://opengameart.org/content/lpc-hair"
      ]
    },
    {
      "file": "hair/curtains/female/white.png",
      "notes": "",
      "authors": [
        "Mandi Paugh",
        "bluecarrot16"
      ],
      "licenses": [
        "GPL 2.0",
        "GPL 3.0",
        "CC-BY 3.0"
      ],
      "urls": [
        "https://opengameart.org/content/star-overland",
        "https://opengameart.org/content/lpc-hair"
      ]
    },
    {
      "file": "hair/curtains/male/red.png",
      "notes": "",
      "authors": [
        "Mandi Paugh",
        "bluecarrot16"
      ],
      "licenses": [
        "GPL 2.0",
        "GPL 3.0",
        "CC-BY 3.0"
      ],
      "urls": [
        "https://opengameart.org/content/star-overland",
        "https://opengameart.org/content/lpc-hair"
      ]
    },
    {
      "file": "hair/curtains/female/red.png",
      "notes": "",
      "authors": [
        "Mandi Paugh",
        "bluecarrot16"
      ],
      "licenses": [
        "GPL 2.0",
        "GPL 3.0",
        "CC-BY 3.0"
      ],
      "urls": [
        "https://opengameart.org/content/star-overland",
        "https://opengameart.org/content/lpc-hair"
      ]
    },
    {
      "file": "hair/curtains/male/orange.png",
      "notes": "",
      "authors": [
        "Mandi Paugh",
        "bluecarrot16"
      ],
      "licenses": [
        "GPL 2.0",
        "GPL 3.0",
        "CC-BY 3.0"
      ],
      "urls": [
        "https://opengameart.org/content/star-overland",
        "https://opengameart.org/content/lpc-hair"
      ]
    },
    {
      "file": "hair/curtains/female/orange.png",
      "notes": "",
      "authors": [
        "Mandi Paugh",
        "bluecarrot16"
      ],
      "licenses": [
        "GPL 2.0",
        "GPL 3.0",
        "CC-BY 3.0"
      ],
      "urls": [
        "https://opengameart.org/content/star-overland",
        "https://opengameart.org/content/lpc-hair"
      ]
    },
    {
      "file": "hair/curtains/male/gold.png",
      "notes": "",
      "authors": [
        "Mandi Paugh",
        "bluecarrot16"
      ],
      "licenses": [
        "GPL 2.0",
        "GPL 3.0",
        "CC-BY 3.0"
      ],
      "urls": [
        "https://opengameart.org/content/star-overland",
        "https://opengameart.org/content/lpc-hair"
      ]
    },
    {
      "file": "hair/curtains/female/gold.png",
      "notes": "",
      "authors": [
        "Mandi Paugh",
        "bluecarrot16"
      ],
      "licenses": [
        "GPL 2.0",
        "GPL 3.0",
        "CC-BY 3.0"
      ],
      "urls": [
        "https://opengameart.org/content/star-overland",
        "https://opengameart.org/content/lpc-hair"
      ]
    },
    {
      "file": "hair/curtains/male/green.png",
      "notes": "",
      "authors": [
        "Mandi Paugh",
        "bluecarrot16"
      ],
      "licenses": [
        "GPL 2.0",
        "GPL 3.0",
        "CC-BY 3.0"
      ],
      "urls": [
        "https://opengameart.org/content/star-overland",
        "https://opengameart.org/content/lpc-hair"
      ]
    },
    {
      "file": "hair/curtains/female/green.png",
      "notes": "",
      "authors": [
        "Mandi Paugh",
        "bluecarrot16"
      ],
      "licenses": [
        "GPL 2.0",
        "GPL 3.0",
        "CC-BY 3.0"
      ],
      "urls": [
        "https://opengameart.org/content/star-overland",
        "https://opengameart.org/content/lpc-hair"
      ]
    },
    {
      "file": "hair/curtains/male/blue.png",
      "notes": "",
      "authors": [
        "Mandi Paugh",
        "bluecarrot16"
      ],
      "licenses": [
        "GPL 2.0",
        "GPL 3.0",
        "CC-BY 3.0"
      ],
      "urls": [
        "https://opengameart.org/content/star-overland",
        "https://opengameart.org/content/lpc-hair"
      ]
    },
    {
      "file": "hair/curtains/female/blue.png",
      "notes": "",
      "authors": [
        "Mandi Paugh",
        "bluecarrot16"
      ],
      "licenses": [
        "GPL 2.0",
        "GPL 3.0",
        "CC-BY 3.0"
      ],
      "urls": [
        "https://opengameart.org/content/star-overland",
        "https://opengameart.org/content/lpc-hair"
      ]
    },
    {
      "file": "hair/curtains/male/navy.png",
      "notes": "",
      "authors": [
        "Mandi Paugh",
        "bluecarrot16"
      ],
      "licenses": [
        "GPL 2.0",
        "GPL 3.0",
        "CC-BY 3.0"
      ],
      "urls": [
        "https://opengameart.org/content/star-overland",
        "https://opengameart.org/content/lpc-hair"
      ]
    },
    {
      "file": "hair/curtains/female/navy.png",
      "notes": "",
      "authors": [
        "Mandi Paugh",
        "bluecarrot16"
      ],
      "licenses": [
        "GPL 2.0",
        "GPL 3.0",
        "CC-BY 3.0"
      ],
      "urls": [
        "https://opengameart.org/content/star-overland",
        "https://opengameart.org/content/lpc-hair"
      ]
    },
    {
      "file": "hair/curtains/male/violet.png",
      "notes": "",
      "authors": [
        "Mandi Paugh",
        "bluecarrot16"
      ],
      "licenses": [
        "GPL 2.0",
        "GPL 3.0",
        "CC-BY 3.0"
      ],
      "urls": [
        "https://opengameart.org/content/star-overland",
        "https://opengameart.org/content/lpc-hair"
      ]
    },
    {
      "file": "hair/curtains/female/violet.png",
      "notes": "",
      "authors": [
        "Mandi Paugh",
        "bluecarrot16"
      ],
      "licenses": [
        "GPL 2.0",
        "GPL 3.0",
        "CC-BY 3.0"
      ],
      "urls": [
        "https://opengameart.org/content/star-overland",
        "https://opengameart.org/content/lpc-hair"
      ]
    },
    {
      "file": "hair/curtains/male/purple.png",
      "notes": "",
      "authors": [
        "Mandi Paugh",
        "bluecarrot16"
      ],
      "licenses": [
        "GPL 2.0",
        "GPL 3.0",
        "CC-BY 3.0"
      ],
      "urls": [
        "https://opengameart.org/content/star-overland",
        "https://opengameart.org/content/lpc-hair"
      ]
    },
    {
      "file": "hair/curtains/female/purple.png",
      "notes": "",
      "authors": [
        "Mandi Paugh",
        "bluecarrot16"
      ],
      "licenses": [
        "GPL 2.0",
        "GPL 3.0",
        "CC-BY 3.0"
      ],
      "urls": [
        "https://opengameart.org/content/star-overland",
        "https://opengameart.org/content/lpc-hair"
      ]
    },
    {
      "file": "hair/curtains/male/pink.png",
      "notes": "",
      "authors": [
        "Mandi Paugh",
        "bluecarrot16"
      ],
      "licenses": [
        "GPL 2.0",
        "GPL 3.0",
        "CC-BY 3.0"
      ],
      "urls": [
        "https://opengameart.org/content/star-overland",
        "https://opengameart.org/content/lpc-hair"
      ]
    },
    {
      "file": "hair/curtains/female/pink.png",
      "notes": "",
      "authors": [
        "Mandi Paugh",
        "bluecarrot16"
      ],
      "licenses": [
        "GPL 2.0",
        "GPL 3.0",
        "CC-BY 3.0"
      ],
      "urls": [
        "https://opengameart.org/content/star-overland",
        "https://opengameart.org/content/lpc-hair"
      ]
    },
    {
      "file": "hair/curtains/male/rose.png",
      "notes": "",
      "authors": [
        "Mandi Paugh",
        "bluecarrot16"
      ],
      "licenses": [
        "GPL 2.0",
        "GPL 3.0",
        "CC-BY 3.0"
      ],
      "urls": [
        "https://opengameart.org/content/star-overland",
        "https://opengameart.org/content/lpc-hair"
      ]
    },
    {
      "file": "hair/curtains/female/rose.png",
      "notes": "",
      "authors": [
        "Mandi Paugh",
        "bluecarrot16"
      ],
      "licenses": [
        "GPL 2.0",
        "GPL 3.0",
        "CC-BY 3.0"
      ],
      "urls": [
        "https://opengameart.org/content/star-overland",
        "https://opengameart.org/content/lpc-hair"
      ]
    }
  ]
}