{
  "name" : "Dragon Tail",
  "type_name" : "tail",
  "layer_1" : {
    "zPos" : 85,
    "male" : "body/tail/dragon/adult_front/",
    "muscular" : "body/tail/dragon/adult_front/",
    "female" : "body/tail/dragon/adult_front/",
    "pregnant" : "body/tail/dragon/adult_front/",
    "teen" : "body/tail/dragon/adult_front/",
    "child" : "body/tail/dragon/child_front/"
  },
  "layer_2" : {
    "zPos" : 5,
    "male" : "body/tail/dragon/adult_back/",
    "muscular" : "body/tail/dragon/adult_back/",
    "female" : "body/tail/dragon/adult_back/",
    "pregnant" : "body/tail/dragon/adult_back/",
    "teen" : "body/tail/dragon/adult_back/",
    "child" : "body/tail/dragon/child_back/"
  },
  "variants": [
    "blonde",
    "ash",
    "sandy",
    "platinum",
    "strawberry",
    "redhead",
    "ginger",
    "carrot",
    "chestnut",
    "light brown",
    "dark brown",
    "black",
    "raven",
    "dark gray",
    "gray",
    "white",
    "red",
    "orange",
    "gold",
    "green",
    "blue",
    "navy",
    "violet",
    "purple",
    "pink",
    "rose"
  ]
}
